HISTORY.md
LICENSE
MANIFEST.in
README.rst
setup.py
arrow/__init__.py
arrow/api.py
arrow/arrow.py
arrow/factory.py
arrow/formatter.py
arrow/locales.py
arrow/parser.py
arrow/util.py
arrow_fatisar.egg-info/PKG-INFO
arrow_fatisar.egg-info/SOURCES.txt
arrow_fatisar.egg-info/dependency_links.txt
arrow_fatisar.egg-info/not-zip-safe
arrow_fatisar.egg-info/requires.txt
arrow_fatisar.egg-info/top_level.txt
docs/Makefile
docs/conf.py
docs/index.rst
docs/_themes/COPYING.txt
docs/_themes/README.rst
docs/_themes/f6/NEWS.txt
docs/_themes/f6/README.rst
docs/_themes/f6/layout.html
docs/_themes/f6/theme.conf
docs/_themes/f6/static/brillant.png
docs/_themes/f6/static/f6.css
tests/__init__.py
tests/api_tests.py
tests/arrow_tests.py
tests/factory_tests.py
tests/formatter_tests.py
tests/locales_tests.py
tests/parser_tests.py
tests/util_tests.py