Metadata-Version: 1.0
Name: arrow-fatisar
Version: 0.5.2
Summary: ("arrow" fork) Better dates and times for Python, with intervals
Home-page: https://github.com/fatisar/arrow
Author: Daniel Sarfati
Author-email: fatisar@gmail.com
License: Apache 2.0
Platform: UNKNOWN
